tmmis/__init__.py
tmmis/admin.py
tmmis/apps.py
tmmis/handlers.py
tmmis/router.py
tmmis/tests.py
tmmis/views.py
tmmis/models/__init__.py
tmmis/models/atf_file_attachment.py
tmmis/models/atf_file_info.py
tmmis/models/atf_file_type.py
tmmis/models/base_model.py
tmmis/models/hlt_blank_template.py
tmmis/models/hlt_call_doctor.py
tmmis/models/hlt_call_doctor_status.py
tmmis/models/hlt_citizen.py
tmmis/models/hlt_disp_result_type.py
tmmis/models/hlt_disp_result_type_value.py
tmmis/models/hlt_disp_result_value.py
tmmis/models/hlt_doc_prvd.py
tmmis/models/hlt_doctor_time_table.py
tmmis/models/hlt_doctor_visit_table.py
tmmis/models/hlt_healing_room.py
tmmis/models/hlt_lpu_doctor.py
tmmis/models/hlt_med_record.py
tmmis/models/hlt_mkab.py
tmmis/models/hlt_mkb_tap.py
tmmis/models/hlt_polis_mkab.py
tmmis/models/hlt_reason_care.py
tmmis/models/hlt_representative_mkab.py
tmmis/models/hlt_smtap.py
tmmis/models/hlt_tap.py
tmmis/models/hlt_type_call_doctor.py
tmmis/models/hlt_uchastok.py
tmmis/models/hlt_visit_history.py
tmmis/models/kla_address.py
tmmis/models/kla_house.py
tmmis/models/kla_kladr.py
tmmis/models/kla_street.py
tmmis/models/lbr_complex_research_type.py
tmmis/models/lbr_histological_block.py
tmmis/models/lbr_lab_direction_type.py
tmmis/models/lbr_lab_research_cause.py
tmmis/models/lbr_lab_research_target.py
tmmis/models/lbr_laboratory.py
tmmis/models/lbr_laboratory_kind.py
tmmis/models/lbr_laboratory_research.py
tmmis/models/lbr_laboratory_research_in_pack.py
tmmis/models/lbr_laboratory_research_pack.py
tmmis/models/lbr_laboratory_research_type.py
tmmis/models/lbr_laboratory_type.py
tmmis/models/lbr_option.py
tmmis/models/lbr_option_enum_values.py
tmmis/models/lbr_option_value.py
tmmis/models/lbr_option_value_type.py
tmmis/models/lbr_research.py
tmmis/models/lbr_research_journal.py
tmmis/models/lbr_research_param_value_type.py
tmmis/models/lbr_research_param_values.py
tmmis/models/lbr_research_result.py
tmmis/models/lbr_research_sample.py
django_tmmis-0.3.17.dist-info/METADATA
django_tmmis-0.3.17.dist-info/WHEEL
django_tmmis-0.3.17.dist-info/top_level.txt
django_tmmis-0.3.17.dist-info/RECORD
